WhatsappLib/__init__.py
WhatsappLib/whatsapplib/__init__.py
WhatsappLib/whatsapplib/preprocess.py
WhatsappLib/whatsapplib/utils.py
WhatsappLib-0.0.5.dist-info/LICENSE
WhatsappLib-0.0.5.dist-info/METADATA
WhatsappLib-0.0.5.dist-info/WHEEL
WhatsappLib-0.0.5.dist-info/top_level.txt
WhatsappLib-0.0.5.dist-info/RECORD
